lexic/__init__.py
lexic-0.0.4.dist-info/METADATA
lexic-0.0.4.dist-info/WHEEL
lexic-0.0.4.dist-info/top_level.txt
lexic-0.0.4.dist-info/RECORD
