Metadata-Version: 2.1
Name: lexic
Version: 0.0.4
Summary: hello package
Home-page: UNKNOWN
Author: nandan
Author-email: <nandanpadia@gmail.com>
License: UNKNOWN
Keywords: c
Platform: UNKNOWN
